InstallerPack/__config__.py
InstallerPack/__init__.py
InstallerPack/installerpack.py
installerpack-0.1.0.dist-info/licenses/LICENSE
installerpack-0.1.0.dist-info/METADATA
installerpack-0.1.0.dist-info/WHEEL
installerpack-0.1.0.dist-info/top_level.txt
installerpack-0.1.0.dist-info/RECORD
