Metadata-Version: 2.4
Name: installerpack
Version: 0.1.0
Summary: InstallerPack is a Python module designed to simplify adding 'Installer' functionality to Python applications. It provides a single function that can be linked to button clicks, enabling cloud-based version updates and seamless rebuilding with `pyinstaller`.
Home-page: https://github.com/TaireruLLC/octastore
Author: Uniplex LLC (formerly Taireru LLC)
Author-email: tairerullc@gmail.com
License: MIT
Classifier: Programming Language :: Python :: 3
Classifier: Operating System :: OS Independent
Requires-Python: >=3.6
License-File: LICENSE
Dynamic: author
Dynamic: author-email
Dynamic: classifier
Dynamic: description
Dynamic: description-content-type
Dynamic: home-page
Dynamic: license
Dynamic: license-file
Dynamic: requires-python
Dynamic: summary
